zachs_pypi_poc_a
