Metadata-Version: 1.0
Name: zachs-pypi-poc-a
Version: 0.8.0
Summary: Pypi proof of concept module
Home-page: UNKNOWN
Author: Zach Harris
Author-email: zharris@talend.com
License: MIT
Platform: UNKNOWN
